RobotFramework_DBus/RobotFramework_DBus.pdf
RobotFramework_DBus/__init__.py
RobotFramework_DBus/dbus_client.py
RobotFramework_DBus/dbus_client_remote.py
RobotFramework_DBus/dbus_manager.py
RobotFramework_DBus/version.py
RobotFramework_DBus/common/__init__.py
RobotFramework_DBus/common/priority_queue.py
RobotFramework_DBus/common/register_keyword.py
RobotFramework_DBus/common/scheduled_job.py
RobotFramework_DBus/common/thread_safe_dict.py
RobotFramework_DBus/common/utils.py
RobotFramework_DBus/dbus_agent/dbus_client_agent.py
robotframework_dbus-0.1.3.dist-info/LICENSE
robotframework_dbus-0.1.3.dist-info/METADATA
robotframework_dbus-0.1.3.dist-info/WHEEL
robotframework_dbus-0.1.3.dist-info/top_level.txt
robotframework_dbus-0.1.3.dist-info/RECORD
