Metadata-Version: 2.1
Name: robotframework-dbus
Version: 0.1.3
Summary: Robot Framework QConnect library extension for dbus testing
Home-page: https://github.com/test-fullautomation/robotframework-dbus
Author: Nguyen Huynh Tri Cuong
Author-email: cuong.nguyenhuynhtri@vn.bosch.com
License: UNKNOWN
Platform: UNKNOWN
Classifier: Programming Language :: Python :: 3
Classifier: License :: OSI Approved :: Apache Software License
Classifier: Operating System :: OS Independent
Classifier: Development Status :: 4 - Beta
Classifier: Intended Audience :: Developers
Classifier: Topic :: Software Development
Requires-Python: >=3.0
License-File: LICENSE
